aiobgjobs/__init__.py
aiobgjobs/dispatcher.py
aiobgjobs/handlers.py
aiobgjobs/jobs.py
aiobgjobs/types.py
aiobgjobs-0.1.6.dist-info/WHEEL
aiobgjobs-0.1.6.dist-info/METADATA
aiobgjobs-0.1.6.dist-info/RECORD
