Metadata-Version: 2.1
Name: aiobgjobs
Version: 0.1.6
Summary: This library is designed for asynchronous execution of scheduled tasks.
Home-page: https://github.com/daniilshamraev/aiobgjobs
Author: daniilsamraev
Author-email: shamraev.2002@gmail.com
Requires-Python: >=3.10,<4.0
Classifier: Programming Language :: Python :: 3
Classifier: Programming Language :: Python :: 3.10
Classifier: Programming Language :: Python :: 3.11
Requires-Dist: pytz (>=2022.7,<2023.0)
Project-URL: Repository, https://github.com/daniilshamraev/aiobgjobs
